sungai/__init__.py
sungai/__main__.py
sungai/sungai.py
tests/__init__.py
tests/test_sungai.py
sungai-0.1.6.dist-info/LICENSE
sungai-0.1.6.dist-info/METADATA
sungai-0.1.6.dist-info/WHEEL
sungai-0.1.6.dist-info/entry_points.txt
sungai-0.1.6.dist-info/top_level.txt
sungai-0.1.6.dist-info/RECORD
