Metadata-Version: 2.1
Name: sungai
Version: 0.1.6
Summary: Sungai is a directory rating tool
Home-page: https://github.com/hugocartwright/sungai
Download-URL: https://pypi.org/project/sungai/
Author: Hugo Cartwright
Author-email: Hugo Cartwright <hugo.cartw@gmail.com>
Maintainer-email: Hugo Cartwright <hugo.cartw@gmail.com>
License: MIT License
Project-URL: source, https://github.com/hugocartwright/sungai.git
Keywords: Python
Classifier: Development Status :: 3 - Alpha
Classifier: Environment :: Console
Classifier: Intended Audience :: Developers
Classifier: License :: OSI Approved :: MIT License
Classifier: Natural Language :: English
Classifier: Operating System :: MacOS :: MacOS X
Classifier: Programming Language :: Python :: 3
Classifier: Programming Language :: Python :: 3.8
Classifier: Programming Language :: Python :: 3.9
Classifier: Programming Language :: Python :: 3.10
Classifier: Programming Language :: Python :: 3.11
Classifier: Topic :: Software Development
Classifier: Topic :: Utilities
Requires-Python: >3.7.0
License-File: LICENSE
Requires-Dist: numpy (==1.24.1)
Requires-Dist: gitignore-parser (==0.1.3)
